{
  "users": [
    {
      "id": 1,
      "first_name": "Rickie",
      "last_name": "Ledstone",
      "address": "Apt 396"
    },
    {
      "id": 2,
      "first_name": "Norby",
      "last_name": "Paynes",
      "address": "Apt 1641"
    },
    {
      "id": 3,
      "first_name": "Lock",
      "last_name": "Rigts",
      "address": "PO Box 11881"
    },
    {
      "id": 4,
      "first_name": "Winn",
      "last_name": "Shurey",
      "address": "13th Floor"
    },
    {
      "id": 5,
      "first_name": "Micheline",
      "last_name": "Handasyde",
      "address": "Apt 673"
    },
    {
      "id": 6,
      "first_name": "Tawsha",
      "last_name": "Digance",
      "address": "PO Box 39649"
    },
    {
      "id": 7,
      "first_name": "Meggie",
      "last_name": "Tackes",
      "address": "Suite 19"
    },
    {
      "id": 8,
      "first_name": "Marchelle",
      "last_name": "Sexstone",
      "address": "Apt 1655"
    },
    {
      "id": 9,
      "first_name": "Waylon",
      "last_name": "Quarlis",
      "address": "Suite 69"
    },
    {
      "id": 10,
      "first_name": "Erin",
      "last_name": "Shears",
      "address": "13th Floor"
    },
    {
      "id": 11,
      "first_name": "Tyrus",
      "last_name": "Gossage",
      "address": "Room 483"
    },
    {
      "id": 12,
      "first_name": "Brianna",
      "last_name": "O'Carmody",
      "address": "PO Box 60914"
    },
    {
      "id": 13,
      "first_name": "Marabel",
      "last_name": "Prattin",
      "address": "PO Box 98523"
    },
    {
      "id": 14,
      "first_name": "Janene",
      "last_name": "Sherbourne",
      "address": "Suite 78"
    },
    {
      "id": 15,
      "first_name": "Lionello",
      "last_name": "Tatlock",
      "address": "15th Floor"
    },
    {
      "id": 16,
      "first_name": "Ivory",
      "last_name": "Stuckley",
      "address": "PO Box 10359"
    },
    {
      "id": 17,
      "first_name": "Phaidra",
      "last_name": "Veysey",
      "address": "7th Floor"
    },
    {
      "id": 18,
      "first_name": "Astra",
      "last_name": "McGilvary",
      "address": "9th Floor"
    },
    {
      "id": 19,
      "first_name": "Cece",
      "last_name": "Beernt",
      "address": "Apt 1493"
    },
    {
      "id": 20,
      "first_name": "Bonni",
      "last_name": "Burghill",
      "address": "Suite 52"
    },
    {
      "id": 21,
      "first_name": "Corri",
      "last_name": "McOwen",
      "address": "PO Box 78186"
    },
    {
      "id": 22,
      "first_name": "Anneliese",
      "last_name": "Laying",
      "address": "9th Floor"
    },
    {
      "id": 23,
      "first_name": "Vance",
      "last_name": "Hullah",
      "address": "Room 1819"
    },
    {
      "id": 24,
      "first_name": "Sargent",
      "last_name": "Montrose",
      "address": "Suite 8"
    },
    {
      "id": 25,
      "first_name": "Robb",
      "last_name": "Flescher",
      "address": "PO Box 8484"
    },
    {
      "id": 26,
      "first_name": "Ellary",
      "last_name": "Streeting",
      "address": "PO Box 82127"
    },
    {
      "id": 27,
      "first_name": "Galen",
      "last_name": "Blunsen",
      "address": "4th Floor"
    },
    {
      "id": 28,
      "first_name": "Edik",
      "last_name": "Union",
      "address": "PO Box 84632"
    },
    {
      "id": 29,
      "first_name": "Aleda",
      "last_name": "Corbie",
      "address": "18th Floor"
    },
    {
      "id": 30,
      "first_name": "Berta",
      "last_name": "Dawber",
      "address": "PO Box 50871"
    },
    {
      "id": 31,
      "first_name": "Rees",
      "last_name": "Whenham",
      "address": "Apt 813"
    },
    {
      "id": 32,
      "first_name": "Jone",
      "last_name": "Newe",
      "address": "Suite 73"
    },
    {
      "id": 33,
      "first_name": "Vonni",
      "last_name": "Noad",
      "address": "Apt 437"
    },
    {
      "id": 34,
      "first_name": "Nada",
      "last_name": "Spickett",
      "address": "Suite 82"
    },
    {
      "id": 35,
      "first_name": "Mort",
      "last_name": "Duligal",
      "address": "Room 1388"
    },
    {
      "id": 36,
      "first_name": "Bibi",
      "last_name": "Pieper",
      "address": "Suite 21"
    },
    {
      "id": 37,
      "first_name": "Stanislaus",
      "last_name": "Santacrole",
      "address": "Room 619"
    },
    {
      "id": 38,
      "first_name": "Octavia",
      "last_name": "Pargiter",
      "address": "PO Box 28088"
    },
    {
      "id": 39,
      "first_name": "Stefan",
      "last_name": "Della",
      "address": "Room 1567"
    },
    {
      "id": 40,
      "first_name": "Orelle",
      "last_name": "Elijah",
      "address": "Room 835"
    },
    {
      "id": 41,
      "first_name": "Lucho",
      "last_name": "Biaggetti",
      "address": "Room 1984"
    },
    {
      "id": 42,
      "first_name": "Benni",
      "last_name": "Bartelet",
      "address": "Suite 85"
    },
    {
      "id": 43,
      "first_name": "Wildon",
      "last_name": "Josilevich",
      "address": "PO Box 51070"
    },
    {
      "id": 44,
      "first_name": "Gates",
      "last_name": "Goves",
      "address": "Suite 15"
    },
    {
      "id": 45,
      "first_name": "Lianne",
      "last_name": "Tassel",
      "address": "3rd Floor"
    },
    {
      "id": 46,
      "first_name": "Harman",
      "last_name": "Challace",
      "address": "6th Floor"
    },
    {
      "id": 47,
      "first_name": "Elizabeth",
      "last_name": "Flowith",
      "address": "PO Box 3494"
    },
    {
      "id": 48,
      "first_name": "Ax",
      "last_name": "Iwanowicz",
      "address": "PO Box 75569"
    },
    {
      "id": 49,
      "first_name": "Wayne",
      "last_name": "Raubheim",
      "address": "Suite 58"
    },
    {
      "id": 50,
      "first_name": "Westleigh",
      "last_name": "Jansie",
      "address": "6th Floor"
    }
  ]
}